{
    "items": [
        {
            "content": "movie",
            "fanart": "https://m.media-amazon.com/images/M/MV5BOThiMzZhY2UtOGNjZC00N2U5LWJkYWQtNmFhYWI4NjU1NzJmXkEyXkFqcGdeQXVyMTAyMTcwMDY1._V1_FMjpg_UX1000_.jpg",
            "imdb": "tt2382320",
            "link": [
                "https://1fichier.com/?8uhypt4uldzd7jv543av"
            ],
            "thumbnail": "https://m.media-amazon.com/images/M/MV5BYWQ2NzQ1NjktMzNkNS00MGY1LTgwMmMtYTllYTI5YzNmMmE0XkEyXkFqcGdeQXVyMjM4NTM5NDY@._V1_FMjpg_UX1000_.jpg",
            "title": "[COLOR=goldenrod]No Time to Die[/COLOR]",
            "type": "item",
            "year": "2021"
        },
        {
            "content": "movie",
            "fanart": "https://img.localcdn.net/m/t/11738830/1.jpg",
            "imdb": "tt11738830",
            "link": [
                "https://1fichier.com/?csqjpd7x5bejdzqkw7fy"
            ],
            "thumbnail": "https://img.localcdn.net/m/t/11738830/1.jpg",
            "title": "[COLOR=goldenrod]The Beta Test[/COLOR]",
            "type": "item",
            "year": "2021"
        },
        {
            "content": "movie",
            "fanart": "https://www.themoviedb.org/t/p/w1280/xfP1vRNKvyOvWNjnd0o7kD6b2RR.jpg",
            "imdb": "tt10687506",
            "link": [
                "https://1fichier.com/?lswyzjh18vgetjw0lize"
            ],
            "thumbnail": "https://www.themoviedb.org/t/p/w1280/xfP1vRNKvyOvWNjnd0o7kD6b2RR.jpg",
            "title": "[COLOR=goldenrod]The Electrical Life of Louis Wain[/COLOR]",
            "type": "item",
            "year": "2021"
        },
        {
            "content": "movie",
            "fanart": "https://img.localcdn.net/m/f/3420504/1.jpg",
            "imdb": "tt3420504",
            "link": [
                "https://1fichier.com/?orkirolwjfrnzynq8ul9"
            ],
            "thumbnail": "https://img.localcdn.net/m/f/3420504/1.jpg",
            "title": "[COLOR=goldenrod]Finch[/COLOR]",
            "type": "item",
            "year": "2021"
        },
        {
            "content": "movie",
            "fanart": "https://img.localcdn.net/m/h/10665338/1.jpg",
            "imdb": "tt10665338",
            "link": [
                "https://1fichier.com/?xqnba6ig2gne2bvppnko"
            ],
            "thumbnail": "https://img.localcdn.net/m/h/10665338/1.jpg",
            "title": "[COLOR=goldenrod]Halloween Kills[/COLOR]",
            "type": "item",
            "year": "2021"
        },
        {
            "content": "movie",
            "fanart": "https://www.themoviedb.org/t/p/w1000_and_h563_face/pVAWkob7vrviUJ0RIextyl5tGXF.jpg",
            "imdb": "tt10515988",
            "link": [
                "https://1fichier.com/?a5cvpb3egkbpniemlmak"
            ],
            "thumbnail": "https://img.localcdn.net/m/p/10515988/1.jpg",
            "title": "[COLOR=goldenrod]Paranormal Activity: Next of Kin[/COLOR]",
            "type": "item",
            "year": "2021"
        },
        {
            "content": "movie",
            "fanart": "https://artworks.thetvdb.com/banners/v4/movie/6187/backgrounds/612249ac4f730.jpg",
            "imdb": "tt1160419",
            "link": [
                "https://1fichier.com/?sb9497qmgs4wscoocc9m"
            ],
            "thumbnail": "https://www.themoviedb.org/t/p/w1280/lr3cYNDlJcpT1EWzFH42aSIvkab.jpg",
            "title": "[COLOR=goldenrod]Dune[/COLOR]",
            "type": "item",
            "year": "2021"
        },
        {
            "content": "movie",
            "fanart": "https://img.localcdn.net/m/c/5748448/1.jpg",
            "imdb": "tt5748448",
            "link": [
                "https://1fichier.com/?nffd7cwv2olha1590byr"
            ],
            "thumbnail": "https://img.localcdn.net/m/c/5748448/1.jpg",
            "title": "[COLOR=goldenrod]Copshop[/COLOR]",
            "type": "item",
            "year": "2021"
        },
        {
            "content": "movie",
            "fanart": "https://img.localcdn.net/m/t/13372794/1.jpg",
            "imdb": "tt13372794",
            "link": [
                "https://1fichier.com/?432cywwodqknuugivdu5"
            ],
            "thumbnail": "https://img.localcdn.net/m/t/13372794/1.jpg",
            "title": "[COLOR=goldenrod]The Manor[/COLOR]",
            "type": "item",
            "year": "2021"
        },
        {
            "content": "movie",
            "fanart": "https://img.localcdn.net/m/m/13372944/1.jpg",
            "imdb": "tt13372944",
            "link": [
                "https://1fichier.com/?dvj9uhyy3df7lq3ufq23"
            ],
            "thumbnail": "https://img.localcdn.net/m/m/13372944/1.jpg",
            "title": "[COLOR=goldenrod]Madres[/COLOR]",
            "type": "item",
            "year": "2021"
        },
        {
            "content": "movie",
            "fanart": "https://img.localcdn.net/m/o/12731980/1.jpg",
            "imdb": "tt12731980",
            "link": [
                "https://1fichier.com/?jaehfk2hc1qzo7yn7xac"
            ],
            "thumbnail": "https://img.localcdn.net/m/o/12731980/1.jpg",
            "title": "[COLOR=goldenrod]Old Henry[/COLOR]",
            "type": "item",
            "year": "2021"
        },
        {
            "content": "movie",
            "fanart": "https://m.media-amazon.com/images/M/MV5BNTg4NzJmYzUtM2FjZS00ZWM2LTk4YmItZWU4OWRmNTE0ZjhkXkEyXkFqcGdeQXVyMzQwMTY2Nzk@._V1_FMjpg_UX1000_.jpg",
            "imdb": "tt11284502",
            "link": [
                "https://1fichier.com/?gt8jrjlmqodg0qhdvcze"
            ],
            "thumbnail": "https://m.media-amazon.com/images/M/MV5BYmE3MGQ1ZjYtODUzZC00OWE2LTgxY2ItMDM4MTIzODY5MDk0XkEyXkFqcGdeQXVyMzQwMTY2Nzk@._V1_FMjpg_UX1000_.jpg",
            "title": "[COLOR=goldenrod]South of Heaven[/COLOR]",
            "type": "item",
            "year": "2021"
        },
        {
            "content": "movie",
            "fanart": "https://www.themoviedb.org/t/p/w1280/qxGRdNeWKQcMg6jJduTthsiBbsd.jpg",
            "imdb": "tt9731534",
            "link": [
                "https://1fichier.com/?0j5qkk3x3j62xmz33jou"
            ],
            "thumbnail": "https://www.themoviedb.org/t/p/w1280/qxGRdNeWKQcMg6jJduTthsiBbsd.jpg",
            "title": "[COLOR=goldenrod]The Night House[/COLOR]",
            "type": "item",
            "year": "2021"
        },
        {
            "content": "movie",
            "fanart": "https://i.imgaa.com/2021/07/25/60fda65d27418752393739.jpg",
            "imdb": "tt10954652",
            "link": [
                "https://1fichier.com/?s9cszr7keyy518plx3rk"
            ],
            "thumbnail": "https://i.imgaa.com/2021/07/25/60fda65d27418752393739.jpg",
            "title": "[COLOR=goldenrod]Old[/COLOR]",
            "type": "item",
            "year": "2021"
        },
        {
            "content": "movie",
            "fanart": "https://img.localcdn.net/m/t/8110232/1.jpg",
            "imdb": "tt8110232",
            "link": [
                "https://1fichier.com/?1sf1uxz9qhgngnx7iiwn"
            ],
            "thumbnail": "https://img.localcdn.net/m/t/8110232/1.jpg",
            "title": "[COLOR=goldenrod]The Many Saints of Newark[/COLOR]",
            "type": "item",
            "year": "2021"
        },
        {
            "content": "movie",
            "fanart": "https://i.imgaa.com/2021/09/11/613ca34f3304a771262588.jpg",
            "imdb": "tt11196036",
            "link": [
                "https://1fichier.com/?y9hxatgtsvyd0dozz9u8"
            ],
            "thumbnail": "https://www.themoviedb.org/t/p/w1280/60AQOrByV9vDCqy6nt4eOroRild.jpg",
            "title": "[COLOR=goldenrod]The Card Counter[/COLOR]",
            "type": "item",
            "year": "2021"
        },
        {
            "content": "movie",
            "fanart": "https://img.localcdn.net/m/q/9054192/1.jpg",
            "imdb": "tt9054192",
            "link": [
                "https://1fichier.com/?buwy666lqns5kh8mj6uf"
            ],
            "thumbnail": "https://img.localcdn.net/m/q/9054192/1.jpg",
            "title": "[COLOR=goldenrod]Queenpins[/COLOR]",
            "type": "item",
            "year": "2021"
        },
        {
            "content": "movie",
            "fanart": "https://www.themoviedb.org/t/p/w1280/acCS12FVUQ7blkC8qEbuXbsWEs2.jpg",
            "imdb": "tt6264654",
            "link": [
                "https://1fichier.com/?wmzpfdbmi27q8311s463"
            ],
            "thumbnail": "https://www.themoviedb.org/t/p/w1280/yc2IfL701hGkNHRgzmF4C6VKO14.jpg",
            "title": "[COLOR=goldenrod]Free Guy[/COLOR]",
            "type": "item",
            "year": "2021"
        },
        {
            "content": "movie",
            "fanart": "https://img.localcdn.net/m/b/11771006/1.jpg",
            "imdb": "tt11771006",
            "link": [
                "https://1fichier.com/?dstzzjuc2q4jp60rkcqi"
            ],
            "thumbnail": "https://img.localcdn.net/m/b/11771006/1.jpg",
            "title": "[COLOR=goldenrod]Birds of Paradise[/COLOR]",
            "type": "item",
            "year": "2021"
        },
        {
            "content": "movie",
            "fanart": "https://img.localcdn.net/m/p/11376010/1.jpg",
            "imdb": "tt11376010",
            "link": [
                "https://1fichier.com/?z27ybftr7gwvpi2ejwhe"
            ],
            "thumbnail": "https://img.localcdn.net/m/p/11376010/1.jpg",
            "title": "[COLOR=goldenrod]People Just Do Nothing: Big in Japan[/COLOR]",
            "type": "item",
            "year": "2021"
        },
        {
            "content": "movie",
            "fanart": "https://i.imgaa.com/2021/09/17/614441f66a596435687417.jpg",
            "imdb": "tt1924245",
            "link": [
                "https://1fichier.com/?cvnwysgqr0z7ju6h4nih"
            ],
            "thumbnail": "https://i.imgaa.com/2021/09/17/614441f66a596435687417.jpg",
            "title": "[COLOR=goldenrod]Cry Macho[/COLOR]",
            "type": "item",
            "year": "2021"
        },
        {
            "content": "movie",
            "fanart": "https://m.media-amazon.com/images/M/MV5BMGI1NGIwMDQtNGZkYS00ZDYyLWIxYmYtMWQzMWVmMDFiN2Q5XkEyXkFqcGdeQXVyMjI3NzE4MTM@._V1_FMjpg_UX1000_.jpg",
            "imdb": "tt9347730",
            "link": [
                "https://1fichier.com/?fzwzc4vxu9v9t4zwnkbt(4K)"
            ],
            "thumbnail": "https://m.media-amazon.com/images/M/MV5BOWEzNDAxYmEtYWU0Zi00ZjZjLTkxY2QtMGY1MjY5ZjVhNDdjXkEyXkFqcGdeQXVyMDM2NDM2MQ@@._V1_FMjpg_UX1000_.jpg",
            "title": "[COLOR=goldenrod]Candyman[/COLOR]",
            "type": "item",
            "year": "2021"
        },
        {
            "content": "movie",
            "fanart": "https://img.localcdn.net/m/m/3811906/1.jpg",
            "imdb": "tt3811906",
            "link": [
                "https://1fichier.com/?ufck3p70fv47ps98whpm"
            ],
            "thumbnail": "https://img.localcdn.net/m/m/3811906/1.jpg",
            "title": "[COLOR=goldenrod]Malignant[/COLOR]",
            "type": "item",
            "year": "2021"
        },
        {
            "content": "movie",
            "fanart": "https://i.imgaa.com/2021/07/08/60e75d167ece0731419435.jpg",
            "imdb": "tt9844522",
            "link": [
                "https://1fichier.com/?6rcs5e8nvairx6rzjmlg"
            ],
            "thumbnail": "https://i.imgaa.com/2021/07/08/60e75d167ece0731419435.jpg",
            "title": "[COLOR=goldenrod]Escape Room: Tournament of Champions(Extended Cut)[/COLOR]",
            "type": "item",
            "year": "2021"
        },
        {
            "content": "movie",
            "fanart": "https://img.localcdn.net/m/d/6246322/1.jpg",
            "imdb": "tt6246322",
            "link": [
                "https://1fichier.com/?x932avnzeg436gysx3k5"
            ],
            "thumbnail": "https://img.localcdn.net/m/d/6246322/1.jpg",
            "title": "[COLOR=goldenrod]Don't Breathe 2[/COLOR]",
            "type": "item",
            "year": "2021"
        },
        {
            "content": "movie",
            "fanart": "https://img.localcdn.net/m/c/10155932/1.jpg",
            "imdb": "tt10155932",
            "link": [
                "https://1fichier.com/?aj4ow64a8xpxdwjjlgj0"
            ],
            "thumbnail": "https://img.localcdn.net/m/c/10155932/1.jpg",
            "title": "[COLOR=goldenrod]Cinderella[/COLOR]",
            "type": "item",
            "year": "2021"
        },
        {
            "content": "movie",
            "fanart": "https://img.localcdn.net/m/r/2452150/1.jpg",
            "imdb": "tt2452150",
            "link": [
                "https://rapidgator.net/file/8dd6d13ac2e02af9bb03157211b1801b"
            ],
            "thumbnail": "https://img.localcdn.net/m/r/2452150/1.jpg",
            "title": "[COLOR=goldenrod]Respect[/COLOR]",
            "type": "item",
            "year": "2021"
        },
        {
            "content": "movie",
            "fanart": "https://img.localcdn.net/m/v/3626476/1.jpg",
            "imdb": "tt3626476",
            "link": [
                "https://1fichier.com/?fjvtwmnzy5zey0nay07b"
            ],
            "thumbnail": "https://img.localcdn.net/m/v/3626476/1.jpg",
            "title": "[COLOR=goldenrod]Vacation Friends[/COLOR]",
            "type": "item",
            "year": "2021"
        },
        {
            "content": "movie",
            "fanart": "https://m.media-amazon.com/images/M/MV5BYWY1N2I5MGUtZTBmNS00MWZmLWEyNzAtZjliNzk0ZDVkYzI1XkEyXkFqcGdeQXVyMTEyMjM2NDc2._V1_.jpg",
            "imdb": "tt6932874",
            "link": [
                "https://1fichier.com/?fu7z2k9xt1j9qnm8h13o"
            ],
            "thumbnail": "https://m.media-amazon.com/images/M/MV5BYWY1N2I5MGUtZTBmNS00MWZmLWEyNzAtZjliNzk0ZDVkYzI1XkEyXkFqcGdeQXVyMTEyMjM2NDc2._V1_.jpg",
            "title": "[COLOR=goldenrod]The Boss Baby Family Business[/COLOR]",
            "type": "item",
            "year": "2021"
        },
        {
            "content": "movie",
            "fanart": "https://m.media-amazon.com/images/M/MV5BZDNmOWM5ODAtZWQ4YS00MGM3LWFlZjgtNmU1ZDM4YmFkNjczXkEyXkFqcGdeQXVyNzIzMTc2Mw@@._V1_.jpg",
            "imdb": "tt8836988",
            "link": [
                "https://1fichier.com/?jf2l9ubyhr46rf31orok"
            ],
            "thumbnail": "https://m.media-amazon.com/images/M/MV5BZDNmOWM5ODAtZWQ4YS00MGM3LWFlZjgtNmU1ZDM4YmFkNjczXkEyXkFqcGdeQXVyNzIzMTc2Mw@@._V1_.jpg",
            "title": "[COLOR=goldenrod]Avengement[/COLOR]",
            "type": "item",
            "year": "2021"
        },
        {
            "content": "movie",
            "fanart": "https://img.localcdn.net/m/p/11832046/1.jpg",
            "imdb": "tt11832046",
            "link": [
                "https://1fichier.com/?6o9uz5n9foi33kdiup9s"
            ],
            "thumbnail": "https://img.localcdn.net/m/p/11832046/1.jpg",
            "title": "[COLOR=goldenrod]PAW Patrol: The Movie[/COLOR]",
            "type": "item",
            "year": "2021"
        },
        {
            "content": "movie",
            "fanart": "https://img.localcdn.net/m/r/3272066/1.jpg",
            "imdb": "tt3272066",
            "link": [
                "https://1fichier.com/?pvdll9zq26k1jy3wrsx9"
            ],
            "thumbnail": "https://img.localcdn.net/m/r/3272066/1.jpg",
            "title": "[COLOR=goldenrod]Reminiscence[/COLOR]",
            "type": "item",
            "year": "2021"
        },
        {
            "content": "movie",
            "fanart": "https://m.media-amazon.com/images/M/MV5BM2JhM2UxMDQtYmJiMS00Y2E3LWExNTgtOWM4MjUzMzdiNzkyXkEyXkFqcGdeQXVyMTEyMjM2NDc2._V1_FMjpg_UX1000_.jpg",
            "imdb": "tt10696896",
            "link": [
                "https://1fichier.com/?4jx9zi844rzfelay27mx"
            ],
            "thumbnail": "https://m.media-amazon.com/images/M/MV5BN2IzMTUyMDUtZGJmZC00YWMzLWFhMGMtZjQwMTkzMzViMjFkXkEyXkFqcGdeQXVyMTEyMjM2NDc2._V1_FMjpg_UX1000_.jpg",
            "title": "[COLOR=goldenrod]Stillwater[/COLOR]",
            "type": "item",
            "year": "2021"
        },
        {
            "content": "movie",
            "fanart": "https://i.imgaa.com/2021/08/01/610713c6a1a68839664538.jpg",
            "imdb": "tt9243804",
            "link": [
                "https://1fichier.com/?d6u118kqyt03vz18bf1v"
            ],
            "thumbnail": "https://i.imgaa.com/2021/08/01/610713c6a1a68839664538.jpg",
            "title": "[COLOR=goldenrod]The Green Knight[/COLOR]",
            "type": "item",
            "year": "2021"
        },
        {
            "content": "movie",
            "fanart": "https://i.imgaa.com/2021/07/26/60fee7e9632c5455826720.jpg",
            "imdb": "tt8404256",
            "link": [
                "https://1fichier.com/?a3tzs0fmdtf05p4t6w3n"
            ],
            "thumbnail": "https://i.imgaa.com/2021/07/26/60fee7e9632c5455826720.jpg",
            "title": "[COLOR=goldenrod]Snake Eyes[/COLOR]",
            "type": "item",
            "year": "2021"
        },
        {
            "content": "movie",
            "fanart": "https://www.themoviedb.org/t/p/w1280/8EnA3iY6o1gDYn0YZA3WtL5Epnj.jpg",
            "imdb": "tt6334354",
            "link": [
                "https://1fichier.com/?hwfvndpdzw3zlqkzoaxz"
            ],
            "thumbnail": "https://www.themoviedb.org/t/p/w1280/464N3J1i6L5SsazPmX9m3q1GiZ3.jpg",
            "title": "[COLOR=goldenrod]The Suicide Squad[/COLOR]",
            "type": "item",
            "year": "2021"
        },
        {
            "content": "movie",
            "fanart": "https://m.media-amazon.com/images/M/MV5BYmI5YTFiNWEtNjg3Mi00ODhmLTkxMTMtYTMyMzU5MjVkMzRkXkEyXkFqcGdeQXVyODk4OTc3MTY@._V1_FMjpg_UX1000_.jpg",
            "imdb": "tt0870154",
            "link": [
                "https://1fichier.com/?u71m8chzaun4pn8vqm4p"
            ],
            "thumbnail": "https://m.media-amazon.com/images/M/MV5BNDE1MGRlNTQtZjc4ZC00MTI0LWEwY2MtODk1YTM2NmFmYTNmXkEyXkFqcGdeQXVyODk4OTc3MTY@._V1_FMjpg_UX1000_.jpg",
            "title": "[COLOR=goldenrod]Jungle Cruise[/COLOR]",
            "type": "item",
            "year": "2021"
        },
        {
            "content": "movie",
            "fanart": "https://i.imgaa.com/2021/07/29/6102343c87a19696911707.jpg",
            "imdb": "tt5433138",
            "link": [
                "https://1fichier.com/?jv0smk3fy3i0ch6d0g0l"
            ],
            "thumbnail": "https://i.imgaa.com/2021/07/29/6102343c87a19696911707.jpg",
            "title": "[COLOR=goldenrod]F9: The Fast Saga[/COLOR]",
            "type": "item",
            "year": "2021"
        },
        {
            "content": "movie",
            "fanart": "https://artworks.thetvdb.com/banners/v4/movie/199629/posters/60dbc8a454fc4.jpg",
            "imdb": "tt10228134",
            "link": [
                "https://1fichier.com/?vqj4amvh2h0i3ag0wyly"
            ],
            "thumbnail": "https://artworks.thetvdb.com/banners/v4/movie/199629/posters/60dbc8a454fc4.jpg",
            "title": "[COLOR=goldenrod]Jolt[/COLOR]",
            "type": "item",
            "year": "2021"
        },
        {
            "content": "movie",
            "fanart": "https://m.media-amazon.com/images/M/MV5BMDQ4YWUwZjItOGUxNy00OTYyLTkxNWQtOWJkMzgxYzI0M2M4XkEyXkFqcGdeQXVyMTEyMjM2NDc2._V1_FMjpg_UX1000_.jpg",
            "imdb": "tt8368408",
            "link": [
                "https://1fichier.com/?ld38zslyivhjtbdqmx43"
            ],
            "thumbnail": "https://m.media-amazon.com/images/M/MV5BYTE4YzczNDQtNmQzNS00ZTZjLThiMzEtOTUzOGQ5ODQzNzY1XkEyXkFqcGdeQXVyMTA3NTQ0Mzkw._V1_FMjpg_UX1000_.jpg",
            "title": "[COLOR=goldenrod]Gunpowder Milkshake[/COLOR]",
            "type": "item",
            "year": "2021"
        },
        {
            "content": "movie",
            "fanart": "https://i.imgaa.com/2021/07/05/60e324b569728920755017.jpg",
            "imdb": "tt10327252",
            "link": [
                "https://1fichier.com/?tkvws5a6n3ulfqmtksmm"
            ],
            "thumbnail": "https://i.imgaa.com/2021/07/05/60e324b569728920755017.jpg",
            "title": "[COLOR=goldenrod]The Forever Purge[/COLOR]",
            "type": "item",
            "year": "2021"
        },
        {
            "content": "movie",
            "fanart": "https://m.media-amazon.com/images/M/MV5BNjI4NGI0ODEtOGE1OC00MmJmLTk0YzQtMmI4NTk5NjVjMzVhXkEyXkFqcGdeQXVyMTI2ODM1ODUw._V1_FMjpg_UX1000_.jpg",
            "imdb": "tt3554046",
            "link": [
                "https://1fichier.com/?fx4izslbgenbbpt7hw4a"
            ],
            "thumbnail": "https://m.media-amazon.com/images/M/MV5BNjg3NmUwYjctMmIzYS00ZTNiLTlhNTYtMWMxNzE5YWIzNmQ4XkEyXkFqcGdeQXVyMTkxNjUyNQ@@._V1_FMjpg_UX1000_.jpg",
            "title": "[COLOR=goldenrod]Space Jam: A New Legacy[/COLOR]",
            "type": "item",
            "year": "2021"
        },
        {
            "content": "movie",
            "fanart": "https://m.media-amazon.com/images/M/MV5BZDg3MmU3MDUtYTFjMi00MGU1LTk2YjktZjM3NjUxYjkxNDQ1XkEyXkFqcGdeQXVyMjQwMDg0Ng@@._V1_FMjpg_UX1000_.jpg",
            "imdb": "tt1697800",
            "link": [
                "https://1fichier.com/?9rrpqeojpkizcqwk080q"
            ],
            "thumbnail": "https://m.media-amazon.com/images/M/MV5BMjViNDU0ZmUtOWRjNS00OGMxLWIzOGEtYzA1ZDA4Y2VhYWYzXkEyXkFqcGdeQXVyMDA4NzMyOA@@._V1_FMjpg_UX1000_.jpg",
            "title": "[COLOR=goldenrod]Die in a Gunfight[/COLOR]",
            "type": "item",
            "year": "2021"
        },
        {
            "content": "movie",
            "fanart": "https://img.localcdn.net/m/h/8355036/1.jpg",
            "imdb": "tt8355036",
            "link": [
                "https://1fichier.com/?jnd7xrbnkb9yqrhjtwjj"
            ],
            "thumbnail": "https://img.localcdn.net/m/h/8355036/1.jpg",
            "title": "[COLOR=goldenrod]How Do You Know Chris?[/COLOR]",
            "type": "item",
            "year": "2021"
        },
        {
            "content": "movie",
            "fanart": "https://www.themoviedb.org/t/p/w1280/oWShnbNGNjsV9vEC5IJ2MWBG5MG.jpg",
            "imdb": "tt9373688",
            "link": [
                "https://1fichier.com/?ja90e9f55bq3qromim62"
            ],
            "thumbnail": "https://www.themoviedb.org/t/p/w1280/d1CViA7W2ZQLodOBWU9bbxnacYY.jpg",
            "title": "[COLOR=goldenrod]Settlers[/COLOR]",
            "type": "item",
            "year": "2021"
        },
        {
            "content": "movie",
            "fanart": "https://artworks.thetvdb.com/banners/movies/27759/backgrounds/5e8a1607b94c4.jpg",
            "imdb": "tt3480822",
            "link": [
                "https://1fichier.com/?zly09b0f8qxmmml9jvcz"
            ],
            "thumbnail": "https://artworks.thetvdb.com/banners/v4/movie/27759/posters/60e0d3f98fa90.jpg",
            "title": "[COLOR=goldenrod]Black Widow[/COLOR]",
            "type": "item",
            "year": "2021"
        },
        {
            "content": "movie",
            "fanart": "https://i.imgaa.com/2021/07/02/60de5848bd24b332006830.jpg",
            "imdb": "tt9777666",
            "link": [
                "https://1fichier.com/?lo8etp73hf6wn7224rv0"
            ],
            "thumbnail": "https://i.imgaa.com/2021/07/02/60de5848bd24b332006830.jpg",
            "title": "[COLOR=goldenrod]The Tomorrow War[/COLOR]",
            "type": "item",
            "year": "2021"
        },
        {
            "content": "movie",
            "fanart": "https://i.imgaa.com/2021/07/01/60ddb98b2461f239422406.jpg",
            "imdb": "tt8376234",
            "link": [
                "https://1fichier.com/?lbojmrht1lk83abdabgc"
            ],
            "thumbnail": "https://i.imgaa.com/2021/07/01/60ddb98b2461f239422406.jpg",
            "title": "[COLOR=goldenrod]Peter Rabbit 2: The Runaway[/COLOR]",
            "type": "item",
            "year": "2021"
        },
        {
            "content": "movie",
            "fanart": "https://i.imgaa.com/2021/07/01/60dd6c401ea87862537050.jpg",
            "imdb": "tt11525644",
            "link": [
                "https://1fichier.com/?g0snu0r53zteesmjp8dy"
            ],
            "thumbnail": "https://i.imgaa.com/2021/07/01/60dd6c401ea87862537050.jpg",
            "title": "[COLOR=goldenrod]No Sudden Move[/COLOR]",
            "type": "item",
            "year": "2021"
        },
        {
            "content": "movie",
            "fanart": "https://i.imgaa.com/2021/05/28/60b09e5cd621d740362615.jpg",
            "imdb": "tt8332922",
            "link": [
                "https://1fichier.com/?2k87esrripytlzrrj39i"
            ],
            "thumbnail": "https://i.imgaa.com/2021/05/28/60b09e5cd621d740362615.jpg",
            "title": "[COLOR=goldenrod]A Quiet Place Part II[/COLOR]",
            "type": "item",
            "year": "2021"
        },
        {
            "content": "movie",
            "fanart": "https://m.media-amazon.com/images/M/MV5BZGIzOWQzZDYtYzY1Yy00YTkyLThkOWItMWI3YjBiMGI4MjllXkEyXkFqcGdeQXVyMTEyMjM2NDc2._V1_FMjpg_UX1000_.jpg",
            "imdb": "tt10096842",
            "link": [
                "https://1fichier.com/?epdhj9n6syizaqx4x0jc"
            ],
            "thumbnail": "https://m.media-amazon.com/images/M/MV5BN2M2N2Q5Y2QtYmI5OS00OWU3LTlkNDgtNWY4YTAwNDFjZmUyXkEyXkFqcGdeQXVyMTkxNjUyNQ@@._V1_FMjpg_UX1000_.jpg",
            "title": "[COLOR=goldenrod]False Positive[/COLOR]",
            "type": "item",
            "year": "2021"
        },
        {
            "content": "movie",
            "fanart": "https://i.imgaa.com/2021/06/25/60d51e91463b4009380105.jpg",
            "imdb": "tt3758814",
            "link": [
                "https://1fichier.com/?yfc9otdjjblbv3dcdje2"
            ],
            "thumbnail": "https://i.imgaa.com/2021/06/25/60d51e91463b4009380105.jpg",
            "title": "[COLOR=goldenrod]The Ice Road[/COLOR]",
            "type": "item",
            "year": "2021"
        },
        {
            "content": "movie",
            "fanart": "https://m.media-amazon.com/images/M/MV5BOWU5MmI3YjktNTBjNi00MWY3LWFkOWQtMjcyZGU1NWNiZGIzXkEyXkFqcGdeQXVyMTIwNDcxNjQ3._V1_FMjpg_UX1000_.jpg",
            "imdb": "tt11084896",
            "link": [
                "https://1fichier.com/?3q4ll2kj6ulkuzv5zrt6"
            ],
            "thumbnail": "https://m.media-amazon.com/images/M/MV5BMDVlZTEwMTItNmE4Zi00ZGFhLWI4NjgtMDdiZTA5NDdmNWYyXkEyXkFqcGdeQXVyMTEyMjM2NDc2._V1_FMjpg_UX1000_.jpg",
            "title": "[COLOR=goldenrod]Spirit Riding Free[/COLOR]",
            "type": "item",
            "year": "2021"
        },
        {
            "content": "movie",
            "fanart": "https://img.localcdn.net/m/l/12801262/1.jpg",
            "imdb": "tt12801262",
            "link": [
                "https://1fichier.com/?ftehp66mx0c5kliiaw5d"
            ],
            "thumbnail": "https://img.localcdn.net/m/l/12801262/1.jpg",
            "title": "[COLOR=goldenrod]Luca[/COLOR]",
            "type": "item",
            "year": "2021"
        },
        {
            "content": "movie",
            "fanart": "https://img.localcdn.net/m/t/10719958/1.jpg",
            "imdb": "tt10719958",
            "link": [
                "https://1fichier.com/?sv2gse1kndum41beb66z"
            ],
            "thumbnail": "https://img.localcdn.net/m/t/10719958/1.jpg",
            "title": "[COLOR=goldenrod]The Birthday Cake[/COLOR]",
            "type": "item",
            "year": "2021"
        },
        {
            "content": "movie",
            "fanart": "https://m.media-amazon.com/images/M/MV5BM2U3NTU4ZTQtNTE0Ny00M2NmLWFhODUtNjYxMDZkZTY3ODZhXkEyXkFqcGdeQXVyODgyODk3MzU@._V1_FMjpg_UX1000_.jpg",
            "imdb": "tt6654210",
            "link": [
                "https://1fichier.com/?vs8now9jzr1i0ybsrubl"
            ],
            "thumbnail": "https://m.media-amazon.com/images/M/MV5BMTNhYzA3ZTctMjU5Zi00MDcxLTlhNTctYWIxMTNjN2YzMGNhXkEyXkFqcGdeQXVyMTA1OTYzOTUx._V1_FMjpg_UX1000_.jpg",
            "title": "[COLOR=goldenrod]Infinite[/COLOR]",
            "type": "item",
            "year": "2021"
        },
        {
            "content": "movie",
            "fanart": "https://m.media-amazon.com/images/M/MV5BOGY0MWQ1M2QtMmI2OC00NGE5LWExZmQtYTI4MzU1MDMyZGJjXkEyXkFqcGdeQXVyMTMyMDM0Nzk3._V1_FMjpg_UX1000_.jpg",
            "imdb": "tt7069210",
            "link": [
                "https://1fichier.com/?5ym1prj64p1aud8gsyc0"
            ],
            "thumbnail": "https://m.media-amazon.com/images/M/MV5BYzQxMjVkZjEtMDQxYy00MGIwLWE1NjYtYzZkZmU1NTFlZGFlXkEyXkFqcGdeQXVyNjY1MTg4Mzc@._V1_FMjpg_UX1000_.jpg",
            "title": "[COLOR=goldenrod]The Conjuring 3: The Devil Made Me Do It[/COLOR]",
            "type": "item",
            "year": "2021"
        },
        {
            "content": "movie",
            "fanart": "https://m.media-amazon.com/images/M/MV5BYzliYmExZjAtN2ZlYy00YzYzLTk2NGUtMDc5Y2Y4NjY0OGY0XkEyXkFqcGdeQXVyMjI3NzE4MTM@._V1_FMjpg_UX1000_.jpg",
            "imdb": "tt10342730",
            "link": [
                "https://1fichier.com/?ezkmjcdmqe72ixf7yjhg"
            ],
            "thumbnail": "https://m.media-amazon.com/images/M/MV5BZjI4ZWQwYzctMGJlMi00OTE1LWFkNjMtY2VlOGQxZmVhNDYyXkEyXkFqcGdeQXVyMjMxOTE0ODA@._V1_FMjpg_UX1000_.jpg",
            "title": "[COLOR=goldenrod]Spiral: From the Book of Saw[/COLOR]",
            "type": "item",
            "year": "2021"
        },
        {
            "content": "movie",
            "fanart": "https://i.imgaa.com/2021/05/28/60b0aa6e84b13416895570.jpg",
            "imdb": "tt3228774",
            "link": [
                "https://1fichier.com/?gdoythnz9v92yjv72ggh"
            ],
            "thumbnail": "https://i.imgaa.com/2021/05/28/60b0aa6e84b13416895570.jpg",
            "title": "[COLOR=goldenrod]Cruella[/COLOR]",
            "type": "item",
            "year": "2021"
        },
        {
            "content": "movie",
            "fanart": "https://www.themoviedb.org/t/p/w1280/YxopfHpsCV1oF8CZaL4M3Eodqa.jpg",
            "imdb": "tt11083552",
            "link": [
                "https://1fichier.com/?gvrb6ridf5wtekrdfx91"
            ],
            "thumbnail": "https://www.themoviedb.org/t/p/w1280/YxopfHpsCV1oF8CZaL4M3Eodqa.jpg",
            "title": "[COLOR=goldenrod]Wrath of Man[/COLOR]",
            "type": "item",
            "year": "2021"
        },
        {
            "content": "movie",
            "fanart": "https://i.imgaa.com/2021/04/03/60689ed45b770430153901.jpg",
            "imdb": "tt9419056",
            "link": [
                "https://1fichier.com/?klhp6fsb8mzpo03b26mk"
            ],
            "thumbnail": "https://i.imgaa.com/2021/04/03/60689ed45b770430153901.jpg",
            "title": "[COLOR=goldenrod]The Unholy[/COLOR]",
            "type": "item",
            "year": "2021"
        },
        {
            "content": "movie",
            "fanart": "https://i.imgaa.com/2021/05/16/60a08380429ba971020560.jpg",
            "imdb": "tt0993840",
            "link": [
                "https://1fichier.com/?xbr0jwbsd489jk3kvlb9"
            ],
            "thumbnail": "https://i.imgaa.com/2021/05/16/60a08380429ba971020560.jpg",
            "title": "[COLOR=goldenrod]Army of the Dead[/COLOR]",
            "type": "item",
            "year": "2021"
        },
        {
            "content": "movie",
            "fanart": "https://i.imgaa.com/2021/05/14/609e6b76d2ae1592388727.jpg",
            "imdb": "tt3215824",
            "link": [
                "https://rg.to/file/c92ba6cbf7af4626d61c9d209a1e4ef6"
            ],
            "thumbnail": "https://i.imgaa.com/2021/05/14/609e6b76d2ae1592388727.jpg",
            "title": "[COLOR=goldenrod]Those Who Wish Me Dead[/COLOR]",
            "type": "item",
            "year": "2021"
        },
        {
            "content": "movie",
            "fanart": "https://www.themoviedb.org/t/p/w1280/iSOKgnlz74ubyKLiMu4ZclHgYh6.jpg",
            "imdb": "tt0499097",
            "link": [
                "https://1fichier.com/?acgapo7q28dnvfoy7twx"
            ],
            "thumbnail": "https://www.themoviedb.org/t/p/w1280/rEm96ib0sPiZBADNKBHKBv5bve9.jpg",
            "title": "[COLOR=goldenrod]Tom Clancy's Without Remorse[/COLOR]",
            "type": "item",
            "year": "2021"
        },
        {
            "content": "movie",
            "fanart": "https://i.imgaa.com/2021/04/23/60824c4aeba1a308494779.jpg",
            "imdb": "tt0293429",
            "link": [
                "https://1fichier.com/?bg01yycw5rtwy9slyqkn"
            ],
            "thumbnail": "https://i.imgaa.com/2021/04/23/60824c4aeba1a308494779.jpg",
            "title": "[COLOR=goldenrod]Mortal Kombat[/COLOR]",
            "type": "item",
            "year": "2021"
        },
        {
            "content": "movie",
            "fanart": "https://www.themoviedb.org/t/p/w1280/4QIe8vtKVNgD7QChden2Xrw4hT0.jpg",
            "imdb": "tt7888964",
            "link": [
                "https://1fichier.com/?epqmzq9qob8od8xus5n6"
            ],
            "thumbnail": "https://www.themoviedb.org/t/p/w1280/oBgWY00bEFeZ9N25wWVyuQddbAo.jpg",
            "title": "[COLOR=goldenrod]Nobody[/COLOR]",
            "type": "item",
            "year": "2021"
        },
        {
            "content": "movie",
            "fanart": "https://i.imgaa.com/2021/03/04/60415bb1ba2a0879019888.jpg",
            "imdb": "tt2076822",
            "link": [
                "http://www.nitroflare.com/view/6C6F21CA224FCF2"
            ],
            "thumbnail": "https://i.imgaa.com/2021/03/04/60415bb1ba2a0879019888.jpg",
            "title": "[COLOR=goldenrod]Chaos Walking[/COLOR]",
            "type": "item",
            "year": "2021"
        },
        {
            "content": "movie",
            "fanart": "https://www.themoviedb.org/t/p/w1280/pgqgaUx1cJb5oZQQ5v0tNARCeBp.jpg",
            "imdb": "tt5034838",
            "link": [
                "https://1fichier.com/?ekf54trtkxxbzhfzwxlu"
            ],
            "thumbnail": "https://www.themoviedb.org/t/p/w1280/pgqgaUx1cJb5oZQQ5v0tNARCeBp.jpg",
            "title": "[COLOR=goldenrod]Godzilla vs. Kong[/COLOR]",
            "type": "item",
            "year": "2021"
        },
        {
            "content": "movie",
            "fanart": "https://m.media-amazon.com/images/M/MV5BNWI5NWVkYTQtOGE3Yy00Y2Q0LTllNjktOWZlYzYwYjEzZjBhXkEyXkFqcGdeQXVyMTkxNjUyNQ@@._V1_FMjpg_UX1000_.jpg",
            "imdb": "tt12361974",
            "link": [
                "https://1fichier.com/?84iv1s9w9l2w52ad0o2j(4k)",
                "https://1fichier.com/?gx7hsr4aszhk0o4i3ffq(4k Gray)"
            ],
            "thumbnail": "https://m.media-amazon.com/images/M/MV5BYjI3NDg0ZTEtMDEwYS00YWMyLThjYjktMTNlM2NmYjc1OGRiXkEyXkFqcGdeQXVyMTEyMjM2NDc2._V1_FMjpg_UX1000_.jpg",
            "title": "[COLOR=goldenrod]Zack Snyder's Justice League[/COLOR]",
            "type": "item",
            "year": "2021"
        },
        {
            "content": "movie",
            "fanart": "https://m.media-amazon.com/images/M/MV5BYjgyYTJkNGYtZjE1Ni00MmRmLWJlOGQtYTMxZTBiZWRmOWRhXkEyXkFqcGdeQXVyMjMxODQ5MDk@._V1_FMjpg_UX1000_.jpg",
            "imdb": "tt9130508",
            "link": [
                "https://1fichier.com/?eysecord2j10q8cf00c4"
            ],
            "thumbnail": "https://m.media-amazon.com/images/M/MV5BOTZkMzlkYmItZDAyNy00NmZhLWE3MWItMzQyNDhkYzcwMTFmXkEyXkFqcGdeQXVyMDM2NDM2MQ@@._V1_FMjpg_UX1000_.jpg",
            "title": "[COLOR=goldenrod]Cherry[/COLOR]",
            "type": "item",
            "year": "2021"
        },
        {
            "content": "movie",
            "fanart": "https://www.themoviedb.org/t/p/w1280/A6fxm71Z5dgHQIx8pyVib5w98eJ.jpg",
            "imdb": "tt8597594",
            "link": [
                "https://1fichier.com/?zwxgl0z4gkyhfkbmd8re"
            ],
            "thumbnail": "https://www.themoviedb.org/t/p/w1280/e2rzzyY2qNJNGE0jhBkTFTjiFpm.jpg",
            "title": "[COLOR=goldenrod]Adverse[/COLOR]",
            "type": "item",
            "year": "2021"
        },
        {
            "content": "movie",
            "fanart": "https://m.media-amazon.com/images/M/MV5BZDE5NjIwYjEtNDQ5MS00MmRhLTkyMzAtMjNlYjI1OWY4ZTBkXkEyXkFqcGdeQXVyODQwOTA4MDg@._V1_FMjpg_UX1000_.jpg",
            "imdb": "tt5109280",
            "link": [
                "https://1fichier.com/?m7kogyzavhiyyjx8nsj6"
            ],
            "thumbnail": "https://m.media-amazon.com/images/M/MV5BYWRjNjFhYjctNGE3ZS00ZWQ5LTkyYTgtNDVhMDM0YTc5YjQ5XkEyXkFqcGdeQXVyMTkxNjUyNQ@@._V1_FMjpg_UX1000_.jpg",
            "title": "[COLOR=goldenrod]Raya and the Last Dragon[/COLOR]",
            "type": "item",
            "year": "2021"
        },
        {
            "content": "movie",
            "fanart": "https://i.imgaa.com/2021/03/05/60417cb3414f7000048279.jpg",
            "imdb": "tt6802400",
            "link": [
                "https://1fichier.com/?cxcsbxyy3gt97t7r458l"
            ],
            "thumbnail": "https://i.imgaa.com/2021/03/05/60417cb3414f7000048279.jpg",
            "title": "[COLOR=goldenrod]Coming 2 America[/COLOR]",
            "type": "item",
            "year": "2021"
        },
        {
            "content": "movie",
            "fanart": "https://www.themoviedb.org/t/p/w1280/a5nlUpWXic3upJkyykMfpwu2t9p.jpg",
            "imdb": "tt4761112",
            "link": [
                "https://1fichier.com/?6u6flqnferkc62hwodol"
            ],
            "thumbnail": "https://www.themoviedb.org/t/p/w1280/a5nlUpWXic3upJkyykMfpwu2t9p.jpg",
            "title": "[COLOR=goldenrod]The Mauritanian[/COLOR]",
            "type": "item",
            "year": "2021"
        },
        {
            "content": "movie",
            "fanart": "https://i.imgaa.com/2021/02/17/602c5dfe0ae20343078316.jpg",
            "imdb": "tt1361336",
            "link": [
                "https://1fichier.com/?dwmy1azbwmpj1ypr3b1d"
            ],
            "thumbnail": "https://i.imgaa.com/2021/02/17/602c5dfe0ae20343078316.jpg",
            "title": "[COLOR=goldenrod]Tom and Jerry[/COLOR]",
            "type": "item",
            "year": "2021"
        },
        {
            "content": "movie",
            "fanart": "https://i.imgaa.com/2021/02/19/602f1e228d561930795161.jpg",
            "imdb": "tt9893250",
            "link": [
                "https://1fichier.com/?m3oianwo4peko8bcc83l"
            ],
            "thumbnail": "https://i.imgaa.com/2021/02/19/602f1e228d561930795161.jpg",
            "title": "[COLOR=goldenrod]I Care a Lot[/COLOR]",
            "type": "item",
            "year": "2021"
        },
        {
            "content": "movie",
            "fanart": "https://m.media-amazon.com/images/M/MV5BNzQ3N2EwYzQtNTVlOC00N2Q4LWI5YTktOTllMDY2NGE5ZDYyXkEyXkFqcGdeQXVyNTM2NTY4NzU@._V1_FMjpg_UX1000_.jpg",
            "imdb": "tt6475714",
            "link": [
                "http://www.nitroflare.com/view/7F22B3869FF50B2"
            ],
            "thumbnail": "https://m.media-amazon.com/images/M/MV5BOGU3NTFmNjYtODc3Ny00MWEzLWI3M2ItZjE3NDgwMTI0MzkzXkEyXkFqcGdeQXVyMTEyMjM2NDc2._V1_FMjpg_UX1000_.jpg",
            "title": "[COLOR=goldenrod]Monster Hunter[/COLOR]",
            "type": "item",
            "year": "2021"
        },
        {
            "content": "movie",
            "fanart": "https://www.themoviedb.org/t/p/w1280/4U1SBHmwHkNA0eHZ2n1CuiC1K1g.jpg",
            "imdb": "tt9110170",
            "link": [
                "https://1fichier.com/?e9ai58q0m0kcvsia4t08"
            ],
            "thumbnail": "https://i.imgaa.com/2021/02/05/601c8c358502f979505415.jpg",
            "title": "[COLOR=goldenrod]Wrong Turn[/COLOR]",
            "type": "item",
            "year": "2021"
        },
        {
            "content": "movie",
            "fanart": "https://i.imgaa.com/2021/02/12/60264bba50f29016395939.jpg",
            "imdb": "tt9784798",
            "link": [
                "https://1fichier.com/?cm7h28yntg5e2glsbh13"
            ],
            "thumbnail": "https://i.imgaa.com/2021/02/12/60264bba50f29016395939.jpg",
            "title": "[COLOR=goldenrod]Judas and the Black Messiah[/COLOR]",
            "type": "item",
            "year": "2021"
        },
        {
            "content": "movie",
            "fanart": "https://i.imgaa.com/2021/02/12/6025df156a56d867342525.jpg",
            "imdb": "tt3797512",
            "link": [
                "https://1fichier.com/?hljeqamoa2ucxhz0bn9u",
                "http://www.nitroflare.com/view/B8333F792FB8310(Debrid)",
                "https://dood.so/d/vbfq69yw5ykb(Non Debrid)"
            ],
            "thumbnail": "https://i.imgaa.com/2021/02/12/6025df156a56d867342525.jpg",
            "title": "[COLOR=goldenrod]Barb and Star Go to Vista Del Mar[/COLOR]",
            "type": "item",
            "year": "2021"
        },
        {
            "content": "movie",
            "fanart": "https://www.themoviedb.org/t/p/w1280/4uWDYzdbyxpX6QOBYx4HoHpksZ8.jpg",
            "imdb": "tt11080108",
            "link": [
                "https://1fichier.com/?yeusaos6i37v7cgciylc"
            ],
            "thumbnail": "https://www.themoviedb.org/t/p/w1280/4uWDYzdbyxpX6QOBYx4HoHpksZ8.jpg",
            "title": "[COLOR=goldenrod]The Map of Tiny Perfect Things[/COLOR]",
            "type": "item",
            "year": "2021"
        },
        {
            "content": "movie",
            "fanart": "https://i.imgaa.com/2021/02/12/60265699db90d563150278.jpg",
            "imdb": "tt7737640",
            "link": [
                "https://1fichier.com/?ii5v5biucwkoozxbhxrl"
            ],
            "thumbnail": "https://i.imgaa.com/2021/02/12/60265699db90d563150278.jpg",
            "title": "[COLOR=goldenrod]Breaking News in Yuba County[/COLOR]",
            "type": "item",
            "year": "2021"
        },
        {
            "content": "movie",
            "fanart": "https://www.themoviedb.org/t/p/w1280/2qOyrIFOwT4oxTmOyg6Fqvs40eK.jpg",
            "imdb": "tt10333426",
            "link": [
                "https://1fichier.com/?hs4ipi4aqlewz9rnavp1"
            ],
            "thumbnail": "https://www.themoviedb.org/t/p/w1280/b7BllsQkD6nTkAdtd28UVCmKqVi.jpg",
            "title": "[COLOR=goldenrod]Bliss[/COLOR]",
            "type": "item",
            "year": "2021"
        },
        {
            "content": "movie",
            "fanart": "https://m.media-amazon.com/images/M/MV5BMDFhYTk4YjktN2QxMC00NDc3LTk2ZTItNDRhNGFkNWQ3ODJhXkEyXkFqcGdeQXVyNjUwNzk3NDc@._V1_FMjpg_UX1000_.jpg",
            "imdb": "tt10016180",
            "link": [
                "https://1fichier.com/?xb8ree9eoh44u9qm539u"
            ],
            "thumbnail": "https://m.media-amazon.com/images/M/MV5BOGFlNTdmYWQtM2IzMi00YTY3LTlmMDQtZDI5NGQ5MjYzZmEwXkEyXkFqcGdeQXVyNjY1MTg4Mzc@._V1_FMjpg_UX1000_.jpg",
            "title": "[COLOR=goldenrod]The Little Things[/COLOR]",
            "type": "item",
            "year": "2021"
        },
        {
            "content": "movie",
            "fanart": "https://m.media-amazon.com/images/M/MV5BM2JkZTJkMTEtOTA3Zi00MWNlLTg4MWYtMGRkYmI1MGJjN2M0XkEyXkFqcGdeQXVyMDM2NDM2MQ@@._V1_FMjpg_UX1000_.jpg",
            "imdb": "tt6857376",
            "link": [
                "https://1fichier.com/?tifd97bnld16vqeb7399"
            ],
            "thumbnail": "https://m.media-amazon.com/images/M/MV5BYTZhNzM4MDktYWUwMC00NTE1LTlkN2UtM2Y5ODIwYjZmNTA2XkEyXkFqcGdeQXVyMDM2NDM2MQ@@._V1_FMjpg_UX1000_.jpg",
            "title": "[COLOR=goldenrod]Palmer[/COLOR]",
            "type": "item",
            "year": "2021"
        },
        {
            "content": "movie",
            "fanart": "https://m.media-amazon.com/images/M/MV5BYTBjZTA3NDYtNzdkYS00M2M5LTlkMjktNmYxMjA2MDlkYWU1XkEyXkFqcGdeQXVyMDM2NDM2MQ@@._V1_FMjpg_UX1000_.jpg",
            "imdb": "tt10451914",
            "link": [
                "https://1fichier.com/?li2wkvxo9m2cir9s0au2"
            ],
            "thumbnail": "https://m.media-amazon.com/images/M/MV5BNmM2MWQ0NzktNzU0OS00MjYzLTkxNDYtMzliNTA5ZmNkMmZlXkEyXkFqcGdeQXVyMDM2NDM2MQ@@._V1_FMjpg_UX1000_.jpg",
            "title": "[COLOR=goldenrod]Outside the Wire[/COLOR]",
            "type": "item",
            "year": "2021"
        },
        {
            "content": "movie",
            "fanart": "https://www.themoviedb.org/t/p/w1280/v9gOSS3cQvUel5MJW6qzGF6eQLh.jpg",
            "imdb": "tt6878306",
            "link": [
                "https://1fichier.com/?nb0ftooe5cigliqil9rz"
            ],
            "thumbnail": "https://www.themoviedb.org/t/p/w1280/fYQCgVRsQTEfUrP7cW5iAFVYOlh.jpg",
            "title": "[COLOR=goldenrod]News of the World[/COLOR]",
            "type": "item",
            "year": "2021"
        },
        {
            "content": "movie",
            "fanart": "https://m.media-amazon.com/images/M/MV5BY2UxOTg2MWMtZGM4Yy00MmQ1LWIxMTUtMzAwNTJiZTgyODExXkEyXkFqcGdeQXVyMDM2NDM2MQ@@._V1_FMjpg_UX1000_.jpg",
            "imdb": "tt11268742",
            "link": [
                "https://1fichier.com/?ng1twxvc1eqgbgpenv3z"
            ],
            "thumbnail": "https://m.media-amazon.com/images/M/MV5BODBjN2ZkYmYtMDA4NS00YmY5LWI1NDktODZmMDM2ZTllZmEzXkEyXkFqcGdeQXVyMDM2NDM2MQ@@._V1_FMjpg_UX1000_.jpg",
            "title": "[COLOR=goldenrod]The Ultimate Playlist of Noise[/COLOR]",
            "type": "item",
            "year": "2021"
        },
        {
            "content": "movie",
            "fanart": "https://image.tmdb.org/t/p/w1280/cjzU4g6SlScnP4MdkleyI25KGlR.jpg",
            "imdb": "tt9620292",
            "link": [
                "https://1fichier.com/?66y3kh6751us0h4gtife"
            ],
            "thumbnail": "https://image.tmdb.org/t/p/w1280/mhJfBitoQ57dCdf9E8zxfUVpSxR.jpg",
            "title": "[COLOR=goldenrod]Promising Young Woman[/COLOR]",
            "type": "item",
            "year": "2021"
        },
        {
            "content": "movie",
            "fanart": "https://www.themoviedb.org/t/p/w1280/l4xgm9BspFnrZ4USbwsnRI97X1p.jpg",
            "imdb": "tt12885852",
            "link": [
                "https://1fichier.com/?rw06jf1ggyfwp5ey8i91"
            ],
            "thumbnail": "https://www.themoviedb.org/t/p/w1280/xQKQVPD0oCMUTNLqswhR8BqaxeU.jpg",
            "title": "[COLOR=goldenrod]Batman: Soul of the Dragon[/COLOR]",
            "type": "item",
            "year": "2021"
        },
        {
            "content": "movie",
            "fanart": "https://m.media-amazon.com/images/M/MV5BOTMyNTM1ZmEtMmI1NS00YjE4LTg1MmMtNjk1NjU3ODI3MTY3XkEyXkFqcGdeQXVyMTEyMjM2NDc2._V1_FMjpg_UX1000_.jpg",
            "imdb": "tt9902160",
            "link": [
                "https://1fichier.com/?yblmlqpkvhm3neu94ip5"
            ],
            "thumbnail": "https://m.media-amazon.com/images/M/MV5BZWJlODA3NzgtNDc5Zi00NzJlLTgyMjMtMDI3MDAxYTVmMjQ3XkEyXkFqcGdeQXVyMTEyMjM2NDc2._V1_FMjpg_UX1000_.jpg",
            "title": "[COLOR=goldenrod]Herself[/COLOR]",
            "type": "item",
            "year": "2021"
        }
    ]
}